twaddle/__init__.py
twaddle/__main__.py
twaddle/compiler/__init__.py
twaddle/compiler/compiler.py
twaddle/compiler/compiler_objects.py
twaddle/compiler/compiler_utils.py
twaddle/default_dictionary/.git
twaddle/default_dictionary/LICENSE
twaddle/default_dictionary/README.md
twaddle/default_dictionary/abstract_nouns.dic
twaddle/default_dictionary/activities.dic
twaddle/default_dictionary/adjective.dic
twaddle/default_dictionary/adverbs.dic
twaddle/default_dictionary/colours.dic
twaddle/default_dictionary/countries.dic
twaddle/default_dictionary/directions.dic
twaddle/default_dictionary/elements.dic
twaddle/default_dictionary/emotions.dic
twaddle/default_dictionary/exclamations.dic
twaddle/default_dictionary/greetings.dic
twaddle/default_dictionary/intransitive_verbs.dic
twaddle/default_dictionary/languages.dic
twaddle/default_dictionary/modals.dic
twaddle/default_dictionary/noun.dic
twaddle/default_dictionary/places.dic
twaddle/default_dictionary/prefixes.dic
twaddle/default_dictionary/relations.dic
twaddle/default_dictionary/substances.dic
twaddle/default_dictionary/timeadv.dic
twaddle/default_dictionary/timenoun.dic
twaddle/default_dictionary/titles.dic
twaddle/default_dictionary/verb.dic
twaddle/default_dictionary/yesno.dic
twaddle/exceptions.py
twaddle/interpreter/__init__.py
twaddle/interpreter/block_attributes.py
twaddle/interpreter/formatter.py
twaddle/interpreter/formatting_object.py
twaddle/interpreter/function_definitions.py
twaddle/interpreter/function_dict.py
twaddle/interpreter/interpreter.py
twaddle/interpreter/regex_state.py
twaddle/interpreter/synchronizer.py
twaddle/lexer/__init__.py
twaddle/lexer/lexer.py
twaddle/lexer/lexer_tokens.py
twaddle/lookup/__init__.py
twaddle/lookup/dictionary_file_parser.py
twaddle/lookup/lookup_dictionary.py
twaddle/lookup/lookup_entry.py
twaddle/lookup/lookup_manager.py
twaddle/py.typed
twaddle/runner.py
twaddle/sample_dicts/adjective.dic
twaddle/sample_dicts/noun.dic
twaddle/sample_dicts/verb.dic
twaddle-1.8.1.dist-info/METADATA
twaddle-1.8.1.dist-info/WHEEL
twaddle-1.8.1.dist-info/licenses/LICENSE
twaddle-1.8.1.dist-info/RECORD
