Metadata-Version: 2.4
Name: twaddle
Version: 1.8.1
Summary: Text generation and templating
License: MIT
License-File: LICENSE
Author: Chris Hengler
Author-email: chrysics@gmail.com
Requires-Python: >=3.11
Classifier: License :: OSI Approved :: MIT License
Classifier: Programming Language :: Python :: 3
Classifier: Programming Language :: Python :: 3.11
Classifier: Programming Language :: Python :: 3.12
Classifier: Programming Language :: Python :: 3.13
Classifier: Programming Language :: Python :: 3.14
Requires-Dist: pytest (>=7.2.0)
Project-URL: Documentation, https://chrishengler.github.io/twaddle/
Project-URL: Repository, https://github.com/chrishengler/twaddle
